geneva/__init__.py
geneva/_context.py
geneva/checkpoint.py
geneva/checkpoint_utils.py
geneva/db.py
geneva/eks.py
geneva/namespace.py
geneva/query.py
geneva/table.py
geneva/transformer.py
geneva/apply/__init__.py
geneva/apply/adaptive.py
geneva/apply/applier.py
geneva/apply/error_handling.py
geneva/apply/multiprocess.py
geneva/apply/simple.py
geneva/apply/task.py
geneva/apply/utils.py
geneva/cloudpickle/__init__.py
geneva/cloudpickle/cloudpickle.py
geneva/cloudpickle/cloudpickle_fast.py
geneva/cluster/__init__.py
geneva/cluster/builder.py
geneva/cluster/mgr.py
geneva/config/__init__.py
geneva/config/base.py
geneva/config/loader.py
geneva/debug/__init__.py
geneva/debug/error_store.py
geneva/debug/job.py
geneva/debug/logger.py
geneva/jobs/__init__.py
geneva/jobs/config.py
geneva/jobs/jobs.py
geneva/manifest/__init__.py
geneva/manifest/builder.py
geneva/manifest/mgr.py
geneva/manifest/uploader_cli.py
geneva/packager/__init__.py
geneva/packager/autodetect.py
geneva/packager/uploader.py
geneva/packager/zip.py
geneva/runners/__init__.py
geneva/runners/kuberay/client.py
geneva/runners/ray/__init__.py
geneva/runners/ray/_mgr.py
geneva/runners/ray/_portforward.py
geneva/runners/ray/actor_pool.py
geneva/runners/ray/admission.py
geneva/runners/ray/jobtracker.py
geneva/runners/ray/kuberay.py
geneva/runners/ray/pipeline.py
geneva/runners/ray/raycluster.py
geneva/runners/ray/writer.py
geneva/state/__init__.py
geneva/state/manager.py
geneva/tqdm/__init__.py
geneva/udfs/__init__.py
geneva/udfs/embeddings.py
geneva/utils/__init__.py
geneva/utils/arrow.py
geneva/utils/batch_size.py
geneva/utils/parse_rust_debug.py
geneva/utils/ray.py
geneva/utils/schema.py
geneva/utils/sequence_queue.py
geneva-0.9.0.dist-info/METADATA
geneva-0.9.0.dist-info/WHEEL
geneva-0.9.0.dist-info/entry_points.txt
geneva-0.9.0.dist-info/licenses/LICENSE
geneva-0.9.0.dist-info/RECORD
